{"title":"BrianaBlair.com - Briana Blair and Kortney Kane - Threesome With","uid":6470435,"size":434324702,"categoryP":"porn","categoryS":"movie_clips","magnet":"?xt=urn:btih:0134610139d3db9ea9cc6e247a1162a5ae3a00d8&amp;dn=BrianaBlair.com+-+Briana+Blair+and+Kortney+Kane+-+Threesome+With&amp;tr=udp%3A%2F%2Ftracker.openbittorrent.com%3A80&amp;tr=udp%3A%2F%2Fopen.demonii.com%3A1337&amp;tr=udp%3A%2F%2Ftracker.coppersurfer.tk%3A6969&amp;tr=udp%3A%2F%2Fexodus.desync.com%3A6969","seeders":0,"leechers":1,"uploader":"beta2008x","files":1,"time":1308125082,"description":" &lt;a href=&quot;http://www.dumppix.com/viewer.php?file=lbsxp_Kortney_Kane_1.jpg&quot; rel=&quot;nofollow&quot; target=&quot;_NEW&quot;&gt;http://www.dumppix.com/viewer.php?file=lbsxp_Kortney_Kane_1.jpg&lt;/a&gt;\n &lt;a href=&quot;\nhttp://www.dumppix.com/viewer.php?file=jhd2n_Kortney_Kane_2.jpg&quot; rel=&quot;nofollow&quot; target=&quot;_NEW&quot;&gt;\nhttp://www.dumppix.com/viewer.php?file=jhd2n_Kortney_Kane_2.jpg&lt;/a&gt;\n &lt;a href=&quot;\nhttp://www.dumppix.com/viewer.php?file=l3h8u_Briana_Blair_Kortney.jpg&quot; rel=&quot;nofollow&quot; target=&quot;_NEW&quot;&gt;\nhttp://www.dumppix.com/viewer.php?file=l3h8u_Briana_Blair_Kortney.jpg&lt;/a&gt;\n\n\nBrianaBlair.com - Briana Blair and Kortney Kane - Threesome With Johnny \n\nReleased : June 14, 2011\n\nMy girl Kortney Kane and I go out for drinks to have some fun and possibly even get lucky! We love going to bars to find hot guys to play with! Our bartender is super hot and definitely feelin' us. We bring him around closer to us and start rubbing up and down his body. He seems to enjoy it so we decide to go for the belt! We share his cock right there at the bar as we play with each other. The night was a success\n\n\n\n\n","torrent":{"xt":"urn:btih:0134610139d3db9ea9cc6e247a1162a5ae3a00d8","amp;dn":"BrianaBlair.com+-+Briana+Blair+and+Kortney+Kane+-+Threesome+With","amp;tr":["udp%3A%2F%2Ftracker.openbittorrent.com%3A80","udp%3A%2F%2Fopen.demonii.com%3A1337","udp%3A%2F%2Ftracker.coppersurfer.tk%3A6969","udp%3A%2F%2Fexodus.desync.com%3A6969"],"infoHash":"0134610139d3db9ea9cc6e247a1162a5ae3a00d8","infoHashBuffer":{"type":"Buffer","data":[1,52,97,1,57,211,219,158,169,204,110,36,122,17,98,165,174,58,0,216]},"announce":[],"urlList":[]}}