{"title":"Quigley.Down.Under.1990.720p.BluRay.X264-AMIABLE","uid":6462922,"size":5929511050,"categoryP":"video","categoryS":"hd___movies","magnet":"?xt=urn:btih:1e44394d67fa15dfc54ca286e0e638753047a41c&amp;dn=Quigley.Down.Under.1990.720p.BluRay.X264-AMIABLE&amp;tr=udp%3A%2F%2Ftracker.openbittorrent.com%3A80&amp;tr=udp%3A%2F%2Fopen.demonii.com%3A1337&amp;tr=udp%3A%2F%2Ftracker.coppersurfer.tk%3A6969&amp;tr=udp%3A%2F%2Fexodus.desync.com%3A6969","seeders":0,"leechers":1,"uploader":"-Gabe-","files":-1,"time":1307846989,"description":" __ .---.\n__ /  `  .-.7,--.\n/  `. .-''. -,  , \\\n'--.-    -;  | ) /\n,` /  \\ ,_) /  '-.\n/  (  (  |  /  .' ) \\          AMIABLE proudly presents:\n'.  `--,/  .---' ,-.|\n`--.  / '-, -' .'              Quigley.Down.Under.1990.720p.BluRay.X264-AMIABLE\n.==,=; `-,.;--'\n/ ,'  _;--;|                    Date .....: 10th June 2011\n/_...=' you are my                Runtime ..: 01:59:55\n        || .==,=.              Size .....: 5.47gb\n        ||/    '.\\            Video ....: 1280x544 (X264 @ 23.976fps)\n        ,||`'=...__\\            Bitrate ..: 5015kbps\n        ||                    Audio ....: DTS 1509kbps\nsweetest downfall..            Source ...: Retail Region A Blu-Ray\n        ||,                    Lang .....: English\n        ||                    Subs .....: English / French / Spanish\n        ,||                    IMDB .....: http://www.imdb.com/title/tt0102744/\n        ||                    Rating ...: 6.6/10 (6,360 votes)\nI loved you first              Screens ..: Opening Week - $3,853,149 (USA) (21 October 1990) (996 Screens)\n        ||                    Genre ....: Western | Adventure | Drama\n        ||,                    Director .: Simon Wincer\n        ||                    Cast .....: Tom Selleck, Laura San Giacomo, Alan Rickman, Chris Haywood\n\n                                    Tomorrow's just your future yesterday!\n\n\n &lt;a href=&quot;\nhttp://shareimage.ro/images/t05ytubqpceatwelkiub.jpg&quot; rel=&quot;nofollow&quot; target=&quot;_NEW&quot;&gt;\nhttp://shareimage.ro/images/t05ytubqpceatwelkiub.jpg&lt;/a&gt;\n\n\n","torrent":{"xt":"urn:btih:1e44394d67fa15dfc54ca286e0e638753047a41c","amp;dn":"Quigley.Down.Under.1990.720p.BluRay.X264-AMIABLE","amp;tr":["udp%3A%2F%2Ftracker.openbittorrent.com%3A80","udp%3A%2F%2Fopen.demonii.com%3A1337","udp%3A%2F%2Ftracker.coppersurfer.tk%3A6969","udp%3A%2F%2Fexodus.desync.com%3A6969"],"infoHash":"1e44394d67fa15dfc54ca286e0e638753047a41c","infoHashBuffer":{"type":"Buffer","data":[30,68,57,77,103,250,21,223,197,76,162,134,224,230,56,117,48,71,164,28]},"announce":[],"urlList":[]}}