{"title":"Pron.The.XXX.Parody.XXX.DVDRip.XviD-STARLETS","uid":6322817,"size":1463216128,"categoryP":"porn","categoryS":"movies","magnet":"?xt=urn:btih:22c52ff2ff80d84d7b0f9cd7caa4031253136ab2&amp;dn=Pron.The.XXX.Parody.XXX.DVDRip.XviD-STARLETS&amp;tr=udp%3A%2F%2Ftracker.openbittorrent.com%3A80&amp;tr=udp%3A%2F%2Fopen.demonii.com%3A1337&amp;tr=udp%3A%2F%2Ftracker.coppersurfer.tk%3A6969&amp;tr=udp%3A%2F%2Fexodus.desync.com%3A6969","seeders":0,"leechers":1,"uploader":"exmnova","files":2,"time":1302992864,"description":"Pron.The.XXX.Parody.XXX.DVDRip.XviD-STARLETS\n\n\n &lt;a href=&quot;\nhttp://0.picswan.com/show.php/5279_3.jpg.html&quot; rel=&quot;nofollow&quot; target=&quot;_NEW&quot;&gt;\nhttp://0.picswan.com/show.php/5279_3.jpg.html&lt;/a&gt;\n\n\n\nMore Info:\n\n\n &lt;a href=&quot;\nhttp://www.69bits.com/torrent/Feature/31633/Pron.The.XXX.Parody.XXX.DVDRip.XviD-STARLETS.html&quot; rel=&quot;nofollow&quot; target=&quot;_NEW&quot;&gt;\nhttp://www.69bits.com/torrent/Feature/31633/Pron.The.XXX.Parody.XXX.DVDRip.XviD-STARLETS.html&lt;/a&gt;","torrent":{"xt":"urn:btih:22c52ff2ff80d84d7b0f9cd7caa4031253136ab2","amp;dn":"Pron.The.XXX.Parody.XXX.DVDRip.XviD-STARLETS","amp;tr":["udp%3A%2F%2Ftracker.openbittorrent.com%3A80","udp%3A%2F%2Fopen.demonii.com%3A1337","udp%3A%2F%2Ftracker.coppersurfer.tk%3A6969","udp%3A%2F%2Fexodus.desync.com%3A6969"],"infoHash":"22c52ff2ff80d84d7b0f9cd7caa4031253136ab2","infoHashBuffer":{"type":"Buffer","data":[34,197,47,242,255,128,216,77,123,15,156,215,202,164,3,18,83,19,106,178]},"announce":[],"urlList":[]}}