{"title":"Once Upon a Time in America (1984) 900p muti [mkvonly]","uid":6495836,"size":17850561460,"categoryP":"video","categoryS":"hd___movies","magnet":"?xt=urn:btih:29d6f8991b85522b98e9a84b2eee5c34bf1f2538&amp;dn=Once+Upon+a+Time+in+America+%281984%29+900p+muti+%5Bmkvonly%5D&amp;tr=udp%3A%2F%2Ftracker.openbittorrent.com%3A80&amp;tr=udp%3A%2F%2Fopen.demonii.com%3A1337&amp;tr=udp%3A%2F%2Ftracker.coppersurfer.tk%3A6969&amp;tr=udp%3A%2F%2Fexodus.desync.com%3A6969","seeders":0,"leechers":1,"uploader":"FatFreddy69","files":-1,"time":1309066440,"description":"Once Upon a Time in America (1984) 900p muti [mkvonly]\n\nFormat                           : Matroska\nFile size                        : 7.88 GiB\nDuration                         : 3h 49mn\nVideo bit rate                   : 4 700 Kbps\nDisplay aspect ratio             : 1600 x 900 (16:9)\nFrame rate                       : 23.976 fps\n\nAudio muxed in English AAC 224 KB/s\n (Decoded/encoded with Sonic/Nero 2 pass, LFE mixed in)\n\nOptional (Separate) Audio Tracks:\n \nEnglish    DTS  768 KB/s, 1.2 GB\nCommentary   AAC 128\nCeska        AC3 640 KB/s, 1 GB\nDeutsch    AC3 640 KB/s, 1 GB\nEspanol    AC3 640 KB/s, 1 GB\nFrancais   AC3 640 KB/s, 1 GB\nItaliano   AC3 640 KB/s, 1 GB\nJapanese   AC3 640 KB/s, 1 GB\n   \n\nUse MPC ( &lt;a href=&quot; http://cccp-project.net/&quot; rel=&quot;nofollow&quot; target=&quot;_NEW&quot;&gt; http://cccp-project.net/&lt;/a&gt;  ) to automatically recognize &amp; play\nthe external Audio tracks or mux the Audio in MKV with  mkvmerge \n( &lt;a href=&quot; http://www.videohelp.com/tools/MKVtoolnix&quot; rel=&quot;nofollow&quot; target=&quot;_NEW&quot;&gt; http://www.videohelp.com/tools/MKVtoolnix&lt;/a&gt;  ) if you wish to use other player.\n\nSubtitles:\nEnglish, Bulgarian, Chinese, Croatian, Czech, Danish, Dutch, Finnish, French, \nGerman, Greek, Hebrew, Hungarian, Italian, Japanese, Korean, Norwegian, Polish, \nPortuguese (Br), Romanian, Spanish (Cast), Swedish, Thai, Turkish \n\n &lt;a href=&quot;\nhttp://www.bilderkiste.org/show/original/6130905479958/1.jpg&quot; rel=&quot;nofollow&quot; target=&quot;_NEW&quot;&gt;\nhttp://www.bilderkiste.org/show/original/6130905479958/1.jpg&lt;/a&gt;\n\n &lt;a href=&quot;\nhttp://www.bilderkiste.org/show/original/6130905491013/2.jpg&quot; rel=&quot;nofollow&quot; target=&quot;_NEW&quot;&gt;\nhttp://www.bilderkiste.org/show/original/6130905491013/2.jpg&lt;/a&gt;\n\n &lt;a href=&quot;\nhttp://www.bilderkiste.org/show/original/5130905494063/3.jpg&quot; rel=&quot;nofollow&quot; target=&quot;_NEW&quot;&gt;\nhttp://www.bilderkiste.org/show/original/5130905494063/3.jpg&lt;/a&gt;\n\n\nExtra: 20 min, 164 MB, AAC 128\nsubs; English, Chinese, Czech, Dutch, French, German, Hungarian,\n Italian, Japanese, Korean, Polish, Portuguese, Spanish, Thai\n\n","torrent":{"xt":"urn:btih:29d6f8991b85522b98e9a84b2eee5c34bf1f2538","amp;dn":"Once+Upon+a+Time+in+America+%281984%29+900p+muti+%5Bmkvonly%5D","amp;tr":["udp%3A%2F%2Ftracker.openbittorrent.com%3A80","udp%3A%2F%2Fopen.demonii.com%3A1337","udp%3A%2F%2Ftracker.coppersurfer.tk%3A6969","udp%3A%2F%2Fexodus.desync.com%3A6969"],"infoHash":"29d6f8991b85522b98e9a84b2eee5c34bf1f2538","infoHashBuffer":{"type":"Buffer","data":[41,214,248,153,27,133,82,43,152,233,168,75,46,238,92,52,191,31,37,56]},"announce":[],"urlList":[]}}