{"title":"1500 Sexy Jessica Alba HQ Photos [Up to 4300 Px]","uid":6477384,"size":649175825,"categoryP":"other","categoryS":"pictures","magnet":"?xt=urn:btih:2d03247f608453bbcd7c56be3f3324768db24daa&amp;dn=1500+Sexy+Jessica+Alba+HQ+Photos+%5BUp+to+4300+Px%5D&amp;tr=udp%3A%2F%2Ftracker.openbittorrent.com%3A80&amp;tr=udp%3A%2F%2Fopen.demonii.com%3A1337&amp;tr=udp%3A%2F%2Ftracker.coppersurfer.tk%3A6969&amp;tr=udp%3A%2F%2Fexodus.desync.com%3A6969","seeders":0,"leechers":1,"uploader":"nico1899","files":2,"time":1308357817,"description":"1500 Sexy Jessica Alba HQ Photos [Up to 4300 Px]\n\n1500 JPG | Up to 4300 Px | 620 Mb","torrent":{"xt":"urn:btih:2d03247f608453bbcd7c56be3f3324768db24daa","amp;dn":"1500+Sexy+Jessica+Alba+HQ+Photos+%5BUp+to+4300+Px%5D","amp;tr":["udp%3A%2F%2Ftracker.openbittorrent.com%3A80","udp%3A%2F%2Fopen.demonii.com%3A1337","udp%3A%2F%2Ftracker.coppersurfer.tk%3A6969","udp%3A%2F%2Fexodus.desync.com%3A6969"],"infoHash":"2d03247f608453bbcd7c56be3f3324768db24daa","infoHashBuffer":{"type":"Buffer","data":[45,3,36,127,96,132,83,187,205,124,86,190,63,51,36,118,141,178,77,170]},"announce":[],"urlList":[]}}