{"title":"Robin Hood (2010) R5 [Actie &amp; Drama] DutchReleaseTeam","uid":5803180,"size":1468215964,"categoryP":"video","categoryS":"movies","magnet":"?xt=urn:btih:42b3160bae29ed3a49231de275be7b718ad8b354&amp;dn=Robin+Hood+%282010%29+R5+%5BActie+%26+Drama%5D+DutchReleaseTeam&amp;tr=udp%3A%2F%2Ftracker.openbittorrent.com%3A80&amp;tr=udp%3A%2F%2Fopen.demonii.com%3A1337&amp;tr=udp%3A%2F%2Ftracker.coppersurfer.tk%3A6969&amp;tr=udp%3A%2F%2Fexodus.desync.com%3A6969","seeders":0,"leechers":1,"uploader":"Koedje","files":6,"time":1283300332,"description":"\n\n\nVerenigde Staten / Verenigd Koninkrijk\nActie / Drama\n148 minuten / 164 minuten (Director's Cut)\n\ngeregisseerd door Ridley Scott\nmet Russell Crowe, Cate Blanchett en Mark Strong\n\nHet legendarische verhaal over de ervaren boogschutter Robin Hood (Russell Crowe), die in dienst treedt bij het leger van koning Richard om tegen de Fransen te vechten. Na de dood van de koning vertrekt Robin naar Nottingham, een stad die lijdt onder de corruptie van een tirannieke schout en torenhoge belastingen. Daar valt hij voor de weduwe Lady Marian (Cate Blanchett), die de identiteit en de motieven van deze kruisridder niet volledig vertrouwt. In de hoop de hand van Lady Marian te winnen en de stedelingen te redden, brengt Robin een bende bij elkaar die uitblinkt in dodelijke vechttrucs en levenslust. Samen vallen ze de rijke bovenklasse aan om het onrecht te herstellen...\n\n\n\n\nDutchReleaseTeam = Hardcoded Dutch Subs\n\nmeer zien? http://multimediacafe.nl","torrent":{"xt":"urn:btih:42b3160bae29ed3a49231de275be7b718ad8b354","amp;dn":"Robin+Hood+%282010%29+R5+%5BActie+%26+Drama%5D+DutchReleaseTeam","amp;tr":["udp%3A%2F%2Ftracker.openbittorrent.com%3A80","udp%3A%2F%2Fopen.demonii.com%3A1337","udp%3A%2F%2Ftracker.coppersurfer.tk%3A6969","udp%3A%2F%2Fexodus.desync.com%3A6969"],"infoHash":"42b3160bae29ed3a49231de275be7b718ad8b354","infoHashBuffer":{"type":"Buffer","data":[66,179,22,11,174,41,237,58,73,35,29,226,117,190,123,113,138,216,179,84]},"announce":[],"urlList":[]}}