{"title":"Snake Bytes TV-S02E33 - 5 Meanest Snakes In The World 480p","uid":6332281,"size":51998587,"categoryP":"video","categoryS":"other","magnet":"?xt=urn:btih:4442651bc059fdd9c7c51dc5cdadd7a79e440421&amp;dn=Snake+Bytes+TV-S02E33+-+5+Meanest+Snakes+In+The+World+480p&amp;tr=udp%3A%2F%2Ftracker.openbittorrent.com%3A80&amp;tr=udp%3A%2F%2Fopen.demonii.com%3A1337&amp;tr=udp%3A%2F%2Ftracker.coppersurfer.tk%3A6969&amp;tr=udp%3A%2F%2Fexodus.desync.com%3A6969","seeders":0,"leechers":1,"uploader":"snakeish","files":1,"time":1303330208,"description":"5 meanest snakes in the world.\nWe take a look and try to handle some of our meanest snakes. These snakes bite us almost everytime take them out. Although most snakes are great pets and super tame, these snakes just have a bad attitude. Snake bites are most likely a part of handling these animals, and you're about to see what it's like handling some of the meanest snakes in the world!","torrent":{"xt":"urn:btih:4442651bc059fdd9c7c51dc5cdadd7a79e440421","amp;dn":"Snake+Bytes+TV-S02E33+-+5+Meanest+Snakes+In+The+World+480p","amp;tr":["udp%3A%2F%2Ftracker.openbittorrent.com%3A80","udp%3A%2F%2Fopen.demonii.com%3A1337","udp%3A%2F%2Ftracker.coppersurfer.tk%3A6969","udp%3A%2F%2Fexodus.desync.com%3A6969"],"infoHash":"4442651bc059fdd9c7c51dc5cdadd7a79e440421","infoHashBuffer":{"type":"Buffer","data":[68,66,101,27,192,89,253,217,199,197,29,197,205,173,215,167,158,68,4,33]},"announce":[],"urlList":[]}}