{"title":"Oprah.Winfrey.2011.05.06.Tom.Hanks.&amp;.Julia.Roberts.HDTV.Xvid-NBC","uid":6373789,"size":367020806,"categoryP":"video","categoryS":"tv_shows","magnet":"?xt=urn:btih:4877691bdfc3e5bc14ca9cad5dd2ff39c773fdbb&amp;dn=Oprah.Winfrey.2011.05.06.Tom.Hanks.%26.Julia.Roberts.HDTV.Xvid-NBC&amp;tr=udp%3A%2F%2Ftracker.openbittorrent.com%3A80&amp;tr=udp%3A%2F%2Fopen.demonii.com%3A1337&amp;tr=udp%3A%2F%2Ftracker.coppersurfer.tk%3A6969&amp;tr=udp%3A%2F%2Fexodus.desync.com%3A6969","seeders":0,"leechers":1,"uploader":"DBaum23","files":-1,"time":1304778329,"description":"Oprah.Winfrey.2011.05.06.Tom.Hanks.&amp;.Julia.Roberts.HDTV.Xvid-NBC\n\nRELEASE INFORMATION\n\nVIDEO FORMAT: Xvid\nVIDEO BITRATE: 1036 kbit/s 2pass VBR\nVIDEO RESOLUTION: 624 x 352\nVIDEO ASPECT: Wide Screen\nVIDEO FPS: 29.970\nAUDIO FORMAT: MP3\nAUDIO BITRATE: 112 kbs\nLANGUAGE: English\nRELEASE 06 May 2011 (USA)\nSOURCE: ATSC/QAM digital 1080i\nRIPPED DATE: 07 May 2011 (USA)\nVIDEO LENGTH: 43 minutes\nGENRE: Talk Show\nURL: http://www.imdb.com/name/nm0001856/\n &lt;a href=&quot;\nhttp://www.oprah.com/showinfo/Tom-Hanks-and-Julia-Roberts-Their-Oprah-Show-Farewell&quot; rel=&quot;nofollow&quot; target=&quot;_NEW&quot;&gt;\nhttp://www.oprah.com/showinfo/Tom-Hanks-and-Julia-Roberts-Their-Oprah-Show-Farewell&lt;/a&gt;\n\nTom Hanks and Julia Roberts\nThe stars of Larry Crowne return to Oprah's stage! Look back at this dynamic duo's favorite, funniest Oprah Show moments.\n\n    Their Oprah Show farewell\n    Julia's and Tom's favorite things","torrent":{"xt":"urn:btih:4877691bdfc3e5bc14ca9cad5dd2ff39c773fdbb","amp;dn":"Oprah.Winfrey.2011.05.06.Tom.Hanks.%26.Julia.Roberts.HDTV.Xvid-NBC","amp;tr":["udp%3A%2F%2Ftracker.openbittorrent.com%3A80","udp%3A%2F%2Fopen.demonii.com%3A1337","udp%3A%2F%2Ftracker.coppersurfer.tk%3A6969","udp%3A%2F%2Fexodus.desync.com%3A6969"],"infoHash":"4877691bdfc3e5bc14ca9cad5dd2ff39c773fdbb","infoHashBuffer":{"type":"Buffer","data":[72,119,105,27,223,195,229,188,20,202,156,173,93,210,255,57,199,115,253,187]},"announce":[],"urlList":[]}}