{"title":"Bubba The Love Sponge RADIOIO Uncensored 4/19/11 WDM","uid":6330718,"size":107823150,"categoryP":"audio","categoryS":"other","magnet":"?xt=urn:btih:563a77d7974b6afc14de4e0b5585dc371656d57b&amp;dn=Bubba+The+Love+Sponge+RADIOIO+Uncensored+4%2F19%2F11+WDM&amp;tr=udp%3A%2F%2Ftracker.openbittorrent.com%3A80&amp;tr=udp%3A%2F%2Fopen.demonii.com%3A1337&amp;tr=udp%3A%2F%2Ftracker.coppersurfer.tk%3A6969&amp;tr=udp%3A%2F%2Fexodus.desync.com%3A6969","seeders":0,"leechers":0,"uploader":"HowardSternBtls","files":2,"time":1303272849,"description":"Bubba The Love Sponge RADIOIO Uncensored 4/19/11 WDM","torrent":{"xt":"urn:btih:563a77d7974b6afc14de4e0b5585dc371656d57b","amp;dn":"Bubba+The+Love+Sponge+RADIOIO+Uncensored+4%2F19%2F11+WDM","amp;tr":["udp%3A%2F%2Ftracker.openbittorrent.com%3A80","udp%3A%2F%2Fopen.demonii.com%3A1337","udp%3A%2F%2Ftracker.coppersurfer.tk%3A6969","udp%3A%2F%2Fexodus.desync.com%3A6969"],"infoHash":"563a77d7974b6afc14de4e0b5585dc371656d57b","infoHashBuffer":{"type":"Buffer","data":[86,58,119,215,151,75,106,252,20,222,78,11,85,133,220,55,22,86,213,123]},"announce":[],"urlList":[]}}