{"title":"Kid Dynamite","uid":5795775,"size":39233036,"categoryP":"audio","categoryS":"music","magnet":"?xt=urn:btih:56da240fdec18c3e308ca45af4ab21107a089ef8&amp;dn=Kid+Dynamite&amp;tr=udp%3A%2F%2Ftracker.openbittorrent.com%3A80&amp;tr=udp%3A%2F%2Fopen.demonii.com%3A1337&amp;tr=udp%3A%2F%2Ftracker.coppersurfer.tk%3A6969&amp;tr=udp%3A%2F%2Fexodus.desync.com%3A6969","seeders":0,"leechers":0,"uploader":"perkkrep","files":20,"time":1283033524,"description":" Kid Dynamite was a Philadelphia-based melodic hardcore band consisting of drummer Dave Wagenschutz, guitarist Dan Yemin, and vocalist Jason Shevchuk, as well as original bassist Steve Farrell and eventual replacement Michael &quot;Spider&quot; Cotterman. The band put out two full-lengths before lead singer Jason Shevchuk left the band in order to finish film/editing school; the act subsequently disbanded. They also featured former members of highly influential New Jersey melodic hardcore outfit Lifetime, and future members of a number of acts including None More Black, Armalite, Paint It Black, Higher Giant, and The Loved Ones.","torrent":{"xt":"urn:btih:56da240fdec18c3e308ca45af4ab21107a089ef8","amp;dn":"Kid+Dynamite","amp;tr":["udp%3A%2F%2Ftracker.openbittorrent.com%3A80","udp%3A%2F%2Fopen.demonii.com%3A1337","udp%3A%2F%2Ftracker.coppersurfer.tk%3A6969","udp%3A%2F%2Fexodus.desync.com%3A6969"],"infoHash":"56da240fdec18c3e308ca45af4ab21107a089ef8","infoHashBuffer":{"type":"Buffer","data":[86,218,36,15,222,193,140,62,48,140,164,90,244,171,33,16,122,8,158,248]},"announce":[],"urlList":[]}}