{"title":"The.Ultimate.Fighter.S13E06.HDTV.XviD-aAF","uid":6368055,"size":391448109,"categoryP":"video","categoryS":"tv_shows","magnet":"?xt=urn:btih:5a1b0b413f24f521e4e5ca6e6c2e27bccf4c93ad&amp;dn=The.Ultimate.Fighter.S13E06.HDTV.XviD-aAF&amp;tr=udp%3A%2F%2Ftracker.openbittorrent.com%3A80&amp;tr=udp%3A%2F%2Fopen.demonii.com%3A1337&amp;tr=udp%3A%2F%2Ftracker.coppersurfer.tk%3A6969&amp;tr=udp%3A%2F%2Fexodus.desync.com%3A6969","seeders":0,"leechers":1,"uploader":"torrentzone","files":31,"time":1304577270,"description":"Torrent Uploaded By https://torrentzone.net \n \n\nLike this torrent? Come Join us at https://torrentzone.net/ For faster downloads, no fakes and NO RARS.\n\n\n We are Building a great community with many torrents AND FASTER DOWNLOADS. Uploads are fast and great quality!","torrent":{"xt":"urn:btih:5a1b0b413f24f521e4e5ca6e6c2e27bccf4c93ad","amp;dn":"The.Ultimate.Fighter.S13E06.HDTV.XviD-aAF","amp;tr":["udp%3A%2F%2Ftracker.openbittorrent.com%3A80","udp%3A%2F%2Fopen.demonii.com%3A1337","udp%3A%2F%2Ftracker.coppersurfer.tk%3A6969","udp%3A%2F%2Fexodus.desync.com%3A6969"],"infoHash":"5a1b0b413f24f521e4e5ca6e6c2e27bccf4c93ad","infoHashBuffer":{"type":"Buffer","data":[90,27,11,65,63,36,245,33,228,229,202,110,108,46,39,188,207,76,147,173]},"announce":[],"urlList":[]}}