{"title":"Best Of Frank Crumit","uid":6386814,"size":74421359,"categoryP":"audio","categoryS":"music","magnet":"?xt=urn:btih:60beb4784750a638582bd98db726257381cb4b1c&amp;dn=Best+Of+Frank+Crumit&amp;tr=udp%3A%2F%2Ftracker.openbittorrent.com%3A80&amp;tr=udp%3A%2F%2Fopen.demonii.com%3A1337&amp;tr=udp%3A%2F%2Ftracker.coppersurfer.tk%3A6969&amp;tr=udp%3A%2F%2Fexodus.desync.com%3A6969","seeders":0,"leechers":1,"uploader":"jonjos1932","files":25,"time":1305229076,"description":"Frank Crumit A Great American Singer- Comedian of the 1920s- 1930s","torrent":{"xt":"urn:btih:60beb4784750a638582bd98db726257381cb4b1c","amp;dn":"Best+Of+Frank+Crumit","amp;tr":["udp%3A%2F%2Ftracker.openbittorrent.com%3A80","udp%3A%2F%2Fopen.demonii.com%3A1337","udp%3A%2F%2Ftracker.coppersurfer.tk%3A6969","udp%3A%2F%2Fexodus.desync.com%3A6969"],"infoHash":"60beb4784750a638582bd98db726257381cb4b1c","infoHashBuffer":{"type":"Buffer","data":[96,190,180,120,71,80,166,56,88,43,217,141,183,38,37,115,129,203,75,28]},"announce":[],"urlList":[]}}