{"title":"The.Middle.S02E21.HDTV.XviD-ASAP","uid":6367475,"size":194556417,"categoryP":"video","categoryS":"tv_shows","magnet":"?xt=urn:btih:8eb542bd3423fb9367ba3c900ccff52f8628f778&amp;dn=The.Middle.S02E21.HDTV.XviD-ASAP&amp;tr=udp%3A%2F%2Ftracker.openbittorrent.com%3A80&amp;tr=udp%3A%2F%2Fopen.demonii.com%3A1337&amp;tr=udp%3A%2F%2Ftracker.coppersurfer.tk%3A6969&amp;tr=udp%3A%2F%2Fexodus.desync.com%3A6969","seeders":0,"leechers":1,"uploader":"TvTeam","files":7,"time":1304563155,"description":". \n  &lt;a href=&quot;\nhttp://www.torrentday.com/&quot; rel=&quot;nofollow&quot; target=&quot;_NEW&quot;&gt;\nhttp://www.torrentday.com/&lt;/a&gt;        :     The Hottest Private Tracker On The Net!!!\n\n\nTo Avoid Fakes, ALWAYS Check That The Torrent Was Added By: TvTeam.\n\n\n               www . TorrentDay . Com \n(((((((((((((= Enjoy No RAR releases =))))))))))))))))))))\n\n...................................NFO:....................................\n\n.\n\n\n\n                                                            \n                                                 \n                                         \n                                    \n                                 \n                            \n                     \n                       \n                      \n                         \n                            \n                          \n                           \n                               \n                   \n                       \n                                       \n                              \n                           \noPi                   \n                \n                            \n           \n                   \n               \n                 \n                                         \n                                                        \n                                                         \n                                                          \n                               The Middle                             \n                                                                         \n\n                          Episode.......: S02E21                          \n                          Release Date..: 2011-05-04                      \n                          Release Size..: 176.00Mb                       \n                        Play Time.....: 20:56                            \n                    Resolution....: 624x352                  \n                  Video Codec...: XVID                    \n             Video Bitrate.: 1008kbps                  \n                 Video Bitrate.: 148 VBR kbps              \n                                                                \n                                                       \n                                             \n                                        \n                          \n             \n            \n            \n                                       \n                                                    \n                                                   \n                                                 \n                                                  \n                                   \n                              \n                   asdx               \n                                          \n                                \n                                      \n                         aSCii  by       \n                         oPi/sAc      \n                            20 11","torrent":{"xt":"urn:btih:8eb542bd3423fb9367ba3c900ccff52f8628f778","amp;dn":"The.Middle.S02E21.HDTV.XviD-ASAP","amp;tr":["udp%3A%2F%2Ftracker.openbittorrent.com%3A80","udp%3A%2F%2Fopen.demonii.com%3A1337","udp%3A%2F%2Ftracker.coppersurfer.tk%3A6969","udp%3A%2F%2Fexodus.desync.com%3A6969"],"infoHash":"8eb542bd3423fb9367ba3c900ccff52f8628f778","infoHashBuffer":{"type":"Buffer","data":[142,181,66,189,52,35,251,147,103,186,60,144,12,207,245,47,134,40,247,120]},"announce":[],"urlList":[]}}