{"title":"Jernanger.2009.Norsk tale.Xvid.saga","uid":5763809,"size":729680728,"categoryP":"video","categoryS":"movies","magnet":"?xt=urn:btih:8eeb7ed0fd1ba5a6bcf2b1af83100b39334ecd54&amp;dn=Jernanger.2009.Norsk+tale.Xvid.saga&amp;tr=udp%3A%2F%2Ftracker.openbittorrent.com%3A80&amp;tr=udp%3A%2F%2Fopen.demonii.com%3A1337&amp;tr=udp%3A%2F%2Ftracker.coppersurfer.tk%3A6969&amp;tr=udp%3A%2F%2Fexodus.desync.com%3A6969","seeders":0,"leechers":0,"uploader":"Sagablanc","files":-1,"time":1281810332,"description":"Jernanger &quot;aka&quot; &quot;The storm in my heart&quot; fra 2009\n\n\nNorsk tale, ingen tekst.\nXvid\n\n\n &lt;a href=&quot;\nhttp://www.imdb.com/title/tt1295087/&quot; rel=&quot;nofollow&quot; target=&quot;_NEW&quot;&gt;\nhttp://www.imdb.com/title/tt1295087/&lt;/a&gt;\n\n\n\nPlease seed!\n","torrent":{"xt":"urn:btih:8eeb7ed0fd1ba5a6bcf2b1af83100b39334ecd54","amp;dn":"Jernanger.2009.Norsk+tale.Xvid.saga","amp;tr":["udp%3A%2F%2Ftracker.openbittorrent.com%3A80","udp%3A%2F%2Fopen.demonii.com%3A1337","udp%3A%2F%2Ftracker.coppersurfer.tk%3A6969","udp%3A%2F%2Fexodus.desync.com%3A6969"],"infoHash":"8eeb7ed0fd1ba5a6bcf2b1af83100b39334ecd54","infoHashBuffer":{"type":"Buffer","data":[142,235,126,208,253,27,165,166,188,242,177,175,131,16,11,57,51,78,205,84]},"announce":[],"urlList":[]}}