{"title":"Danni Minogue - I Begin To Wonder","uid":5788446,"size":63010612,"categoryP":"video","categoryS":"music_videos","magnet":"?xt=urn:btih:98ec66e75acdc2d4fb9ef47630d695c800df4d59&amp;dn=Danni+Minogue+-+I+Begin+To+Wonder&amp;tr=udp%3A%2F%2Ftracker.openbittorrent.com%3A80&amp;tr=udp%3A%2F%2Fopen.demonii.com%3A1337&amp;tr=udp%3A%2F%2Ftracker.coppersurfer.tk%3A6969&amp;tr=udp%3A%2F%2Fexodus.desync.com%3A6969","seeders":0,"leechers":0,"uploader":"PardonMeAgain","files":1,"time":1282743002,"description":"music video","torrent":{"xt":"urn:btih:98ec66e75acdc2d4fb9ef47630d695c800df4d59","amp;dn":"Danni+Minogue+-+I+Begin+To+Wonder","amp;tr":["udp%3A%2F%2Ftracker.openbittorrent.com%3A80","udp%3A%2F%2Fopen.demonii.com%3A1337","udp%3A%2F%2Ftracker.coppersurfer.tk%3A6969","udp%3A%2F%2Fexodus.desync.com%3A6969"],"infoHash":"98ec66e75acdc2d4fb9ef47630d695c800df4d59","infoHashBuffer":{"type":"Buffer","data":[152,236,102,231,90,205,194,212,251,158,244,118,48,214,149,200,0,223,77,89]},"announce":[],"urlList":[]}}