{"title":"Natural.World.S30E03.Sea.Otters-A.Million.Dollar.Baby.720p.HDTV.","uid":5764312,"size":1564478813,"categoryP":"video","categoryS":"hd___tv_shows","magnet":"?xt=urn:btih:9bbd46b578b8c09c7dc30e3a93a6f5117a5723a0&amp;dn=Natural.World.S30E03.Sea.Otters-A.Million.Dollar.Baby.720p.HDTV.&amp;tr=udp%3A%2F%2Ftracker.openbittorrent.com%3A80&amp;tr=udp%3A%2F%2Fopen.demonii.com%3A1337&amp;tr=udp%3A%2F%2Ftracker.coppersurfer.tk%3A6969&amp;tr=udp%3A%2F%2Fexodus.desync.com%3A6969","seeders":0,"leechers":0,"uploader":"TvTeam","files":4,"time":1281830666,"description":". \n  &lt;a href=&quot;\nhttp://www.torrentday.com/&quot; rel=&quot;nofollow&quot; target=&quot;_NEW&quot;&gt;\nhttp://www.torrentday.com/&lt;/a&gt;        :     The Hottest Private Tracker On The Net!!!\n\n\nTo Avoid Fakes, ALWAYS Check That The Torrent Was Added By: TvTeam.\n\n\n               www . TorrentDay . Com \n(((((((((((((= Enjoy No RAR releases =))))))))))))))))))))\n\n...................................NFO:....................................\n\n.        \n       \n                                                                \n                                                             \n                                                           \n                                                           \n                                                         \n                                      \n                                       \n                                        \n                                             \n                                            \n                                               \n                                        \n                                     \n                                             \n                                           \n                                         \n                                           \n                                          \n                                \n                              \n                               \n                                \n                                \n                            \n                          \n                                  \n                                 \n                                  \n                             \n                    \n                      \n                                                \n                                 \n                            \n                           \n                                      \n                              \n                                  \n                           \n                          \n                             \n                                    \n                          \n                            \n                       \n                             \n                                 \n                                  \n                                                          \n                                   \n                                \n                       ZNi'02              \n                                         \n                                         \n                                                   \n                                    \n                              \n                             \n                                               \n        \n    \n                                                          \n               .  . ..: SciFiManiacs :.. .  .              \n                                                            \n   Bringing you the best from the world of SciFi and more!  \n                                                            \n                                                \n         . ..: RELEASE iNFORMATiON :.. .   \n\n      \n                                                             \n               Series : Natural World                         \n                Title : Sea Otters - A Million Dollar Baby     \n       Episode Number : S030E03 (3/14) 2010-2011 Season       \n                Genre : Documentary                          \n             iMDB URL : n/a                                   \n             Air Date : 08/12/2010 (SD) 08/13/2010 (HD)        \n         DVD Rel Date : n/a                                   \n         SFM Rel Date : 08/14/2010                           \n            Ripped By : SFM                                   \n               Source : High Definition                        \n         Video Format : x264 (in matroska container)          \n     Video Resolution : 1280x720 (25 fps)                    \n        Video Bitrate : 2 Pass @ 3179 kb/s AVG                \n        Audio Bitrate : AC3 2.0 @ 192 kb/s AVG                 \n          Sample Rate : 48 kHz                                \n               Length : 58 MiN 32 SECS                       \n                 Size : 1.45 GB (1,564,467,903 bytes)         \n              MD5 Sum : ffc79ee53651daa4eb5cd5dd34ec92e0       \n                Packs : 32 x 50MB                             \n                                                             \n      \n\n      \n               .  . ..: EPiSODE SUMMARY :.. .  .             \n                                                              \n    The trials and tribulations of a sea otter pup growing     \n    up on the coast of California.                            \n    The Californian sea otter is one of the rarest, and      \n    possibly cutest animals in the world. So when a sea       \n    otter mum decides to have her pup amongst the yachts of    \n    a millionaires' marina, it is a unique event. The mum     \n    must teach her baby how to dodge the boats and find the  \n    food in this busy harbour. However, the arrival of a      \n    tough male sea otter signals disaster for the family.      \n    When mum is attacked, the poor pup is left on her own     \n    and must fight for survival.                             \n      \n\n      \n            .  . ..: RiPPER/RELEASE NOTES :.. .  .           \n                                                              \n     The BBC classify this episode as episode 3 of the         \n     2010-2011 season, TVRage lists it as 29x17, bu the       \n     previous run from 2009-2010 season was S29 so this by   \n     all rights should be S30, however this could all change  \n     at a later date, as usual it's a mess, something else to  \n     be aware of is not all episodes seem to air in HD with   \n     this particular series.                                 \n      \n\n                                             \n                  ..: GROUP NEWS/CONTACT :..  \n                                                           \n                                                      \n       SFM is dedicated to bringing you high quality     \n      TVRips and DVDRips of popular series and movies for   \n                     your viewing pleasure!                 \n                                                           \n       We are currently looking for:                       \n       - 100+ Mbit EU dump site for exclusive SFM usage   \n       - HDTV/PDTV cappers                                \n       - Crates &amp; Kegs of Beer (full of course)          \n                                                         \n                  .  . ..: GREETZ :.. .  .","torrent":{"xt":"urn:btih:9bbd46b578b8c09c7dc30e3a93a6f5117a5723a0","amp;dn":"Natural.World.S30E03.Sea.Otters-A.Million.Dollar.Baby.720p.HDTV.","amp;tr":["udp%3A%2F%2Ftracker.openbittorrent.com%3A80","udp%3A%2F%2Fopen.demonii.com%3A1337","udp%3A%2F%2Ftracker.coppersurfer.tk%3A6969","udp%3A%2F%2Fexodus.desync.com%3A6969"],"infoHash":"9bbd46b578b8c09c7dc30e3a93a6f5117a5723a0","infoHashBuffer":{"type":"Buffer","data":[155,189,70,181,120,184,192,156,125,195,14,58,147,166,245,17,122,87,35,160]},"announce":[],"urlList":[]}}