{"title":"Wild.Orchid.1989.Swesub.DVDrip.Xvid.AC3-Haggebulle","uid":6467869,"size":1471286800,"categoryP":"video","categoryS":"movies","magnet":"?xt=urn:btih:9e8a0db4ff16b4b5222e9d6f6b517c254bfa250f&amp;dn=Wild.Orchid.1989.Swesub.DVDrip.Xvid.AC3-Haggebulle&amp;tr=udp%3A%2F%2Ftracker.openbittorrent.com%3A80&amp;tr=udp%3A%2F%2Fopen.demonii.com%3A1337&amp;tr=udp%3A%2F%2Ftracker.coppersurfer.tk%3A6969&amp;tr=udp%3A%2F%2Fexodus.desync.com%3A6969","seeders":0,"leechers":1,"uploader":"haggebull","files":-1,"time":1308028876,"description":"Den unga advokaten Emily bÃƒÂ¶rjar ett nytt jobb och fÃƒÂ¥r i uppdrag att fÃƒÂ¶lja med affÃƒÂ¤rskvinnan Claudia till Rio de Janeiro. DÃƒÂ¤r sammanfÃƒÂ¶rs hon med Wheeler, en fÃƒÂ¶rmÃƒÂ¶gen och kÃƒÂ¤nslokall man. Han utnyttjar henne alltmer fÃƒÂ¶r sina voyeuristiska behov, liksom han tidigare utnyttjat Claudia. Men Emily lyckas sprÃƒÂ¤cka hans skal och nÃƒÂ¥ in till hans verkliga kÃƒÂ¤nslor. \n","torrent":{"xt":"urn:btih:9e8a0db4ff16b4b5222e9d6f6b517c254bfa250f","amp;dn":"Wild.Orchid.1989.Swesub.DVDrip.Xvid.AC3-Haggebulle","amp;tr":["udp%3A%2F%2Ftracker.openbittorrent.com%3A80","udp%3A%2F%2Fopen.demonii.com%3A1337","udp%3A%2F%2Ftracker.coppersurfer.tk%3A6969","udp%3A%2F%2Fexodus.desync.com%3A6969"],"infoHash":"9e8a0db4ff16b4b5222e9d6f6b517c254bfa250f","infoHashBuffer":{"type":"Buffer","data":[158,138,13,180,255,22,180,181,34,46,157,111,107,81,124,37,75,250,37,15]},"announce":[],"urlList":[]}}