{"title":"Stationary Pack v 2.6 (2806) with SK patch","uid":6388580,"size":92373494,"categoryP":"applications","categoryS":"mac","magnet":"?xt=urn:btih:c6167719123794ad5a959c5db89c98219f9572df&amp;dn=Stationary+Pack+v+2.6+%282806%29+with+SK+patch&amp;tr=udp%3A%2F%2Ftracker.openbittorrent.com%3A80&amp;tr=udp%3A%2F%2Fopen.demonii.com%3A1337&amp;tr=udp%3A%2F%2Ftracker.coppersurfer.tk%3A6969&amp;tr=udp%3A%2F%2Fexodus.desync.com%3A6969","seeders":0,"leechers":0,"uploader":"polisdavid","files":-1,"time":1305282040,"description":"OfficiaL Web  SIte:  &lt;a href=&quot; http://www.equinux.com/us/products/stationery/index.html&quot; rel=&quot;nofollow&quot; target=&quot;_NEW&quot;&gt; http://www.equinux.com/us/products/stationery/index.html&lt;/a&gt;\n\nDo you still write ordinary emails?\n\nThe Stationery Pack browser opens up a whole new world of correspondence to you: Expand Leopard and Snow Leopard Mail with more than 250 high quality email templates for every possible occasion. The first Stationery Pack is for Mac users who want to create sophisticated email/\n\nStationery Pack 2 is for users with high standards in email design and technology; and there are theme specific Stationery Collections like Season's Greetings or Love &amp; Romance for Valentine's Day. Discover the next generation of email. Discover Stationery Pack.\n\nSystem Requirements:  \n\nMac OS X 10.5 or later\nMail (Part of Mac OS X 10.5)\nPowerPC G4 or higher\n\n--- PLEASE SEED --- ","torrent":{"xt":"urn:btih:c6167719123794ad5a959c5db89c98219f9572df","amp;dn":"Stationary+Pack+v+2.6+%282806%29+with+SK+patch","amp;tr":["udp%3A%2F%2Ftracker.openbittorrent.com%3A80","udp%3A%2F%2Fopen.demonii.com%3A1337","udp%3A%2F%2Ftracker.coppersurfer.tk%3A6969","udp%3A%2F%2Fexodus.desync.com%3A6969"],"infoHash":"c6167719123794ad5a959c5db89c98219f9572df","infoHashBuffer":{"type":"Buffer","data":[198,22,119,25,18,55,148,173,90,149,156,93,184,156,152,33,159,149,114,223]},"announce":[],"urlList":[]}}