{"title":"Saint Seiya: Losta Canvas ep 14 al 17","uid":6332812,"size":1197847165,"categoryP":"video","categoryS":"tv_shows","magnet":"?xt=urn:btih:dcb7610cc9afda2a98a1d0ab79920f9ac40bcab5&amp;dn=Saint+Seiya%3A+Losta+Canvas+ep+14+al+17&amp;tr=udp%3A%2F%2Ftracker.openbittorrent.com%3A80&amp;tr=udp%3A%2F%2Fopen.demonii.com%3A1337&amp;tr=udp%3A%2F%2Ftracker.coppersurfer.tk%3A6969&amp;tr=udp%3A%2F%2Fexodus.desync.com%3A6969","seeders":0,"leechers":0,"uploader":"chrisden33","files":9,"time":1303349830,"description":"Segunda temporada de Saint Seiya: The Lost Canvas, los videos los descargue de esta pagina (thepiratebay.se) por sepaado, los subtitulos en espaÃƒÂ±ol de otro logar, los junte y ahora los comparto.","torrent":{"xt":"urn:btih:dcb7610cc9afda2a98a1d0ab79920f9ac40bcab5","amp;dn":"Saint+Seiya%3A+Losta+Canvas+ep+14+al+17","amp;tr":["udp%3A%2F%2Ftracker.openbittorrent.com%3A80","udp%3A%2F%2Fopen.demonii.com%3A1337","udp%3A%2F%2Ftracker.coppersurfer.tk%3A6969","udp%3A%2F%2Fexodus.desync.com%3A6969"],"infoHash":"dcb7610cc9afda2a98a1d0ab79920f9ac40bcab5","infoHashBuffer":{"type":"Buffer","data":[220,183,97,12,201,175,218,42,152,161,208,171,121,146,15,154,196,11,202,181]},"announce":[],"urlList":[]}}