{"title":"Death Warrior (2009) English+Spanish DD5.1 English Subs NTSC --T","uid":6386391,"size":4520217892,"categoryP":"video","categoryS":"movies_dvdr","magnet":"?xt=urn:btih:f1bccc1ae2dd219c3a03302ce13aa991d4c30446&amp;dn=Death+Warrior+%282009%29+English%2BSpanish+DD5.1+English+Subs+NTSC+--T&amp;tr=udp%3A%2F%2Ftracker.openbittorrent.com%3A80&amp;tr=udp%3A%2F%2Fopen.demonii.com%3A1337&amp;tr=udp%3A%2F%2Ftracker.coppersurfer.tk%3A6969&amp;tr=udp%3A%2F%2Fexodus.desync.com%3A6969","seeders":0,"leechers":1,"uploader":"Saggin","files":-1,"time":1305212144,"description":"Death Warrior (2009) English+Spanish DD5.1 English Subs NTSC\n\n\nNederlands:       \n\nVerenigde Staten / Canada\nActie / Horror\n90 minuten\n\ngeregisseerd door Bill Corcoran\nmet Hector Echavarria, Nick Mancuso en Tanya Clarke\n\nDe kampioen MMA, Reinero (Echavarria), wordt op een hele valse manier de \nonderwereld ingelokt om hier deel te nemen aan illegale gevechten. Hij zal zijn \nvrouw moeten zien te redden uit de handen van een crimineel meesterbrein. In een \nwanhopige race tegen de tijd, zal hij alles moeten geven...\n &lt;a href=&quot;\nhttp://www.moviemeter.nl/film/73248&quot; rel=&quot;nofollow&quot; target=&quot;_NEW&quot;&gt;\nhttp://www.moviemeter.nl/film/73248&lt;/a&gt;\n\nEnglish :\n\nUSA / Canada\nAction / Horror\n90 minutes\n\ndirected by Bill Corcoran\nHector Echavarria, Nick Mancuso and Tanya Clarke\n\nThe MMA champion, Reinero (Echavarria), is a very false way of the underworld \nare lured to participate in illegal fights. He will have to rescue his wife from \nthe hands of a criminal mastermind. In a desperate race against time, he will \nhave to give everything ... \n &lt;a href=&quot;\nhttp://www.imdb.com/title/tt1144797/&quot; rel=&quot;nofollow&quot; target=&quot;_NEW&quot;&gt;\nhttp://www.imdb.com/title/tt1144797/&lt;/a&gt;\n\n\nSpotinformatie\nBron             : DVD\nFormaat          : DVD5\nBeeldverhouding  : 4:3\nFramerate        : 29,970 fps\nStandaard        : NTSC\nVideo            : CCE\nAudio            : DD 5.1  Engels/Spanish\nOndertitels      : ned,eng\nMenu             : ja\nExtra's          : ja","torrent":{"xt":"urn:btih:f1bccc1ae2dd219c3a03302ce13aa991d4c30446","amp;dn":"Death+Warrior+%282009%29+English%2BSpanish+DD5.1+English+Subs+NTSC+--T","amp;tr":["udp%3A%2F%2Ftracker.openbittorrent.com%3A80","udp%3A%2F%2Fopen.demonii.com%3A1337","udp%3A%2F%2Ftracker.coppersurfer.tk%3A6969","udp%3A%2F%2Fexodus.desync.com%3A6969"],"infoHash":"f1bccc1ae2dd219c3a03302ce13aa991d4c30446","infoHashBuffer":{"type":"Buffer","data":[241,188,204,26,226,221,33,156,58,3,48,44,225,58,169,145,212,195,4,70]},"announce":[],"urlList":[]}}